rapidflow/__init__.py
rapidflow/config.py
rapidflow/metrics_handler.py
rapidflow/nn_model.py
rapidflow/objective.py
rapidflow/classifiers/__init__.py
rapidflow/classifiers/k_rank_classifier.py
rapidflow/classifiers/theshold_brute_force_classifier.py
rapidflow/experiments/__init__.py
rapidflow/experiments/experiment.py
rapidflow/experiments/experiment_study.py
rapidflow/experiments/study_result_saver.py
rapidflow/models/__init__.py
rapidflow/models/graph_neural_networks/__init__.py
rapidflow/models/graph_neural_networks/layers/GAT_layer.py
rapidflow/models/graph_neural_networks/layers/__init__.py
rapidflow/models/graph_neural_networks/layers/layers.py
rapidflow/models/neural_networks/__init__.py
rapidflow/models/neural_networks/autoencoder.py
rapidflow/utils/__init__.py
rapidflow/utils/experiment_logger.py
rapidflow-0.1.8.dist-info/LICENSE
rapidflow-0.1.8.dist-info/METADATA
rapidflow-0.1.8.dist-info/WHEEL
rapidflow-0.1.8.dist-info/top_level.txt
rapidflow-0.1.8.dist-info/RECORD
