Metadata-Version: 2.1
Name: rapidflow
Version: 0.1.8
Summary: rapidFlow - A framework to perform micro experimentation fast with easy scaling.
Home-page: https://github.com/gebauerm/rapidFlow
Download-URL: https://github.com/gebauerm/rapidFlow/archive/0.1.8.tar.gz
Author: Michael Gebauer
Author-email: gebauerm23@gmail.com
License: MIT
Classifier: Development Status :: 3 - Alpha
Classifier: Intended Audience :: Developers
Classifier: Topic :: Software Development :: Build Tools
Classifier: License :: OSI Approved :: MIT License
Classifier: Programming Language :: Python :: 3
Requires-Python: >=3.7
License-File: LICENSE
Requires-Dist: optuna (>=2.9.1)
Requires-Dist: click (>=8.0.1)
Requires-Dist: scikit-learn
Requires-Dist: scipy
Requires-Dist: networkx (>=2.5.1)
Requires-Dist: psycopg2-binary
Requires-Dist: docker (>=5.0.3)
Requires-Dist: pandas
Requires-Dist: tqdm (>=4.62.3)
Provides-Extra: test
Requires-Dist: pytest (>=6.2.5) ; extra == 'test'
